factiva/analytics/__init__.py
factiva/analytics/__version__.py
factiva/analytics/bulknews.py
factiva/analytics/log.py
factiva/analytics/stream_response.py
factiva/analytics/auth/__init__.py
factiva/analytics/auth/oauthuser.py
factiva/analytics/auth/userkey.py
factiva/analytics/const/__init__.py
factiva/analytics/const/errors.py
factiva/analytics/dicts/__init__.py
factiva/analytics/req/__init__.py
factiva/analytics/snapshot/__init__.py
factiva/analytics/snapshot/jobs.py
factiva/analytics/snapshot/query.py
factiva/analytics/snapshot/snapshot.py
factiva/analytics/stream/__init__.py
factiva/analytics/stream/listener.py
factiva/analytics/stream/stream.py
factiva/analytics/stream/subscription.py
factiva/analytics/taxonomy/__init__.py
factiva/analytics/taxonomy/company.py
factiva/analytics/taxonomy/taxonomy.py
factiva/analytics/tools/__init__.py
factiva/analytics/tools/bq_schemas.py
factiva/analytics/tools/files.py
factiva/analytics/tools/listener_handlers.py
factiva_analytics-0.3.0.dist-info/LICENSE
factiva_analytics-0.3.0.dist-info/METADATA
factiva_analytics-0.3.0.dist-info/WHEEL
factiva_analytics-0.3.0.dist-info/top_level.txt
factiva_analytics-0.3.0.dist-info/RECORD
